pusher_websocket/__init__.py
pusher_websocket/websocket_override.py
pusher_websocket-0.1.dist-info/LICENSE
pusher_websocket-0.1.dist-info/METADATA
pusher_websocket-0.1.dist-info/WHEEL
pusher_websocket-0.1.dist-info/top_level.txt
pusher_websocket-0.1.dist-info/RECORD
